LICENSE
README.md
setup.py
tensor_sensor.egg-info/PKG-INFO
tensor_sensor.egg-info/SOURCES.txt
tensor_sensor.egg-info/dependency_links.txt
tensor_sensor.egg-info/requires.txt
tensor_sensor.egg-info/top_level.txt
tsensor/__init__.py
tsensor/analysis.py
tsensor/ast.py
tsensor/parsing.py
tsensor/version.py
tsensor/viz.py