Metadata-Version: 2.1
Name: tensor-sensor
Version: 0.1.3
Summary: The goal of this library is to generate more helpful exception messages for numpy/pytorch tensor algebra expressions.
Home-page: https://github.com/parrt/tensor-sensor
Author: Terence Parr
Author-email: parrt@cs.usfca.edu
License: MIT
Platform: UNKNOWN
Classifier: License :: OSI Approved :: MIT License
Classifier: Intended Audience :: Developers
Requires-Python: >=3.6
Provides-Extra: all
Provides-Extra: torch
Provides-Extra: tensorflow
Provides-Extra: jax
License-File: LICENSE
